ddhi_encoder/__init__.py
ddhi_encoder/convert.py
ddhi_encoder/convert_directory.py
ddhi_encoder/generate_standoff.py
ddhi_encoder/interview.py
ddhi_encoder/interview_generator.py
ddhi_encoder/mentioned_events.py
ddhi_encoder/mentioned_orgs.py
ddhi_encoder/mentioned_persons.py
ddhi_encoder/mentioned_places.py
ddhi_encoder/ne_extractor.py
ddhi_encoder/ne_tagger.py
ddhi_encoder/skeleton.py
ddhi_encoder/tag_interview.py
ddhi_encoder/teitemplate.xml
ddhi_encoder/test_interview_generator.py
ddhi_encoder/update_events.py
ddhi_encoder/update_orgs.py
ddhi_encoder/update_persons.py
ddhi_encoder/update_places.py
ddhi_encoder/utterance.py
ddhi_encoder/word_parser.py
ddhi_encoder/aggregators/aggregators.py
ddhi_encoder/entities/entities.py
ddhi_encoder/modifiers/modifiers.py
ddhi_encoder/standoff_generator/standoff_generator.py
ddhi_encoder/transformer/__init__.py
ddhi_encoder/transformer/transformer.py
ddhi_encoder-1.3.0.dist-info/AUTHORS.rst
ddhi_encoder-1.3.0.dist-info/LICENSE.txt
ddhi_encoder-1.3.0.dist-info/METADATA
ddhi_encoder-1.3.0.dist-info/WHEEL
ddhi_encoder-1.3.0.dist-info/entry_points.txt
ddhi_encoder-1.3.0.dist-info/top_level.txt
ddhi_encoder-1.3.0.dist-info/RECORD
