Metadata-Version: 2.1
Name: ddhi-encoder
Version: 1.3.0
Summary: Encoding tools for DDHI
Home-page: https://github.com/agile-humanities/ddhi-encoder/
Author: Clifford Wulfman
Author-email: cliff@agilehumanities.ca
License: mit
Project-URL: Documentation, https://github.com/agile-humanities/ddhi-encoder/blob/master/README.rst
Platform: any
Classifier: Development Status :: 4 - Beta
Classifier: Programming Language :: Python
Requires-Python: >=3.6
License-File: LICENSE.txt
License-File: AUTHORS.rst
Requires-Dist: docx2python (>=1.19.0)
Requires-Dist: lxml (>=4.6.2)
Requires-Dist: spacy (>=3.1.0)
Provides-Extra: testing
Requires-Dist: pytest ; extra == 'testing'
Requires-Dist: pytest-cov ; extra == 'testing'
